funapi/__init__.py
funworld-0.0.1.dist-info/LICENSE
funworld-0.0.1.dist-info/METADATA
funworld-0.0.1.dist-info/WHEEL
funworld-0.0.1.dist-info/entry_points.txt
funworld-0.0.1.dist-info/top_level.txt
funworld-0.0.1.dist-info/RECORD
