Metadata-Version: 2.1
Name: funworld
Version: 0.0.1
Summary: funworld
Home-page: https://github.com/farfarfun/funworld
Author: bingtao
Author-email: 1007530194@qq.com
License-File: LICENSE
Requires-Dist: funpypi
Requires-Dist: funfile
Requires-Dist: requests
Requires-Dist: tqdm
